{
  "timelines": {
    "culture": {
      "title": "Writing & Design",
      "yPosition": 0.3,
      "color": [
        "#FFCB41",
        "#FCB38A"
      ],
      "isGlobal": false
    },
    "lifestyle": {
      "title": "Everyday Media",
      "yPosition": 0.5,
      "color": [
        "#F56F6F",
        "#FF9838"
      ],
      "isGlobal": false
    },
    "highlights": {
      "title": "Media Milestones",
      "yPosition": 0.7,
      "color": [
        "#9C4A80",
        "#769BE8"
      ],
      "isGlobal": false
    },
    "global": {
      "title": "World Context",
      "yPosition": 0.95,
      "color": [
        "#F2E5DF",
        "#EADFDA"
      ],
      "isGlobal": true
    }
  },
  "events": [
    {
      "title": "Cave Paintings as Record",
      "intro": "<p>Early pictorial marks store shared meaning on durable surfaces.</p><p>Pictorial recording precedes formal writing.</p>",
      "timeline": "culture",
      "year": -2000,
      "year_name": "",
      "year_end": 0,
      "country": [
        "FR"
      ],
      "country_name": "Europe",
      "hidden_tags": "Cave Paintings as Record",
      "id": "m001",
      "url": "./events/m001",
      "highlight": false,
      "accuracy": false,
      "filters": [
        "aron"
      ],
      "img": "./assets/images/placeholders/m001.svg"
    },
    {
      "title": "Cuneiform on Clay",
      "intro": "<p>Administrative marks on clay tablets become a durable writing system for trade, law, and myth.</p><p>Early cuneiform begins as pictographic accountancy and evolves into a flexible script pressed into wet clay — one of the first scalable media for institutional memory.</p>",
      "timeline": "culture",
      "year": -2000,
      "year_name": "",
      "year_end": 0,
      "country": [
        "IQ"
      ],
      "country_name": "Sumer",
      "hidden_tags": "writing",
      "id": "e01",
      "url": "./events/e01",
      "highlight": false,
      "accuracy": false,
      "filters": [
        "aron"
      ],
      "img": "./assets/images/placeholders/e01.svg"
    },
    {
      "title": "Egyptian Hieroglyphs",
      "intro": "<p>Monumental and administrative writing systems encode language in sacred and civic contexts.</p><p>Hieroglyphic, hieratic, and later demotic scripts show how medium (stone, papyrus) shapes formality, speed, and audience.</p>",
      "timeline": "culture",
      "year": -2000,
      "year_name": "",
      "year_end": 0,
      "country": [
        "EG"
      ],
      "country_name": "Egypt",
      "hidden_tags": "writing",
      "id": "e02",
      "url": "./events/e02",
      "highlight": false,
      "accuracy": false,
      "filters": [
        "aron"
      ],
      "img": "./assets/images/placeholders/e02.svg"
    },
    {
      "title": "Oracle Bone Script",
      "intro": "<p>Divination inscriptions become an early Chinese writing corpus.</p><p>Bones and shells preserve administrative language.</p>",
      "timeline": "culture",
      "year": -1200,
      "year_name": "",
      "year_end": 0,
      "country": [
        "CN"
      ],
      "country_name": "China",
      "hidden_tags": "Oracle Bone Script",
      "id": "m002",
      "url": "./events/m002",
      "highlight": false,
      "accuracy": false,
      "filters": [
        "aron"
      ],
      "img": "./assets/images/placeholders/m002.svg"
    },
    {
      "title": "Phoenician Alphabet",
      "intro": "<p>A compact consonant alphabet spreads along trade routes and seeds later Mediterranean scripts.</p><p>Fewer signs lower the barrier to literacy compared with logo-syllabic systems, accelerating cross-cultural exchange.</p>",
      "timeline": "culture",
      "year": -1050,
      "year_name": "",
      "year_end": 0,
      "country": [
        "LB"
      ],
      "country_name": "Levant",
      "hidden_tags": "writing",
      "id": "e03",
      "url": "./events/e03",
      "highlight": false,
      "accuracy": false,
      "filters": [
        "aron"
      ],
      "img": "./assets/images/placeholders/e03.svg"
    },
    {
      "title": "Greek Vowels Added",
      "intro": "<p>Adaptation of Phoenician letters adds explicit vowels, clarifying spoken language in text.</p><p>The Greek alphabet becomes a template for Etruscan and Latin scripts that later dominate European media.</p>",
      "timeline": "culture",
      "year": -800,
      "year_name": "",
      "year_end": 0,
      "country": [
        "GR"
      ],
      "country_name": "Greece",
      "hidden_tags": "writing",
      "id": "e04",
      "url": "./events/e04",
      "highlight": false,
      "accuracy": false,
      "filters": [
        "aron"
      ],
      "img": "./assets/images/placeholders/e04.svg"
    },
    {
      "title": "Library of Ashurbanipal",
      "intro": "<p>A royal clay-tablet collection concentrates knowledge.</p><p>Catalogued tablets model institutional memory.</p>",
      "timeline": "culture",
      "year": -650,
      "year_name": "",
      "year_end": 0,
      "country": [
        "IQ"
      ],
      "country_name": "Nineveh",
      "hidden_tags": "Library of Ashurbanipal",
      "id": "m003",
      "url": "./events/m003",
      "highlight": false,
      "accuracy": false,
      "filters": [
        "aron"
      ],
      "img": "./assets/images/placeholders/m003.svg"
    },
    {
      "title": "Library of Alexandria",
      "intro": "<p>A vast collection and research center models knowledge as curated, copyable archive.</p><p>Scroll acquisition, cataloging, and scholarly commentary foreshadow later libraries, encyclopedias, and research networks.</p>",
      "timeline": "culture",
      "year": -280,
      "year_name": "",
      "year_end": 0,
      "country": [
        "EG"
      ],
      "country_name": "Egypt",
      "hidden_tags": "writing, journalism",
      "id": "e05",
      "url": "./events/e05",
      "highlight": false,
      "accuracy": false,
      "filters": [
        "aron",
        "popular"
      ],
      "img": "./assets/images/placeholders/e05.svg"
    },
    {
      "title": "Roman Road Posts & Cursus",
      "intro": "<p>Imperial courier systems move official messages across a continent-scale network.</p><p>Relay stations and road infrastructure turn distance into a managed latency problem — proto-telecom logistics.</p>",
      "timeline": "lifestyle",
      "year": 50,
      "year_name": "",
      "year_end": 0,
      "country": [
        "IT"
      ],
      "country_name": "Roman Empire",
      "hidden_tags": "postal",
      "id": "e06",
      "url": "./events/e06",
      "highlight": false,
      "accuracy": false,
      "filters": [
        "hagira"
      ],
      "img": "./assets/images/placeholders/e06.svg"
    },
    {
      "title": "Paper Invented in China",
      "intro": "<p>Plant-fiber sheets lower the cost of portable text.</p><p>Paper outcompetes papyrus and parchment across Eurasia.</p>",
      "timeline": "culture",
      "year": 105,
      "year_name": "",
      "year_end": 0,
      "country": [
        "CN"
      ],
      "country_name": "China",
      "hidden_tags": "Paper Invented in China",
      "id": "m004",
      "url": "./events/m004",
      "highlight": false,
      "accuracy": false,
      "filters": [
        "rites",
        "aron"
      ],
      "img": "./assets/images/placeholders/m004.svg"
    },
    {
      "title": "Codex Replaces Scroll",
      "intro": "<p>Bound pages enable random access, marginalia, and portable libraries.</p><p>The codex form factor reshapes reading habits and later becomes the default metaphor for books and documents.</p>",
      "timeline": "culture",
      "year": 300,
      "year_name": "",
      "year_end": 0,
      "country": [
        "IT"
      ],
      "country_name": "Mediterranean",
      "hidden_tags": "writing, design",
      "id": "e07",
      "url": "./events/e07",
      "highlight": false,
      "accuracy": false,
      "filters": [
        "aron",
        "arts"
      ],
      "img": "./assets/images/placeholders/e07.svg"
    },
    {
      "title": "Paper Travels West",
      "intro": "<p>Papermaking techniques move along trade routes, lowering the cost of writing surfaces.</p><p>Cheaper substrates expand who can produce and store documents beyond elite parchment economies.</p>",
      "timeline": "culture",
      "year": 750,
      "year_name": "",
      "year_end": 0,
      "country": [
        "ES"
      ],
      "country_name": "Central Asia / Iberia",
      "hidden_tags": "print, writing",
      "id": "e08",
      "url": "./events/e08",
      "highlight": false,
      "accuracy": false,
      "filters": [
        "rites",
        "aron"
      ],
      "img": "./assets/images/placeholders/e08.svg"
    },
    {
      "title": "Woodblock Printing",
      "intro": "<p>The Diamond Sutra and related prints demonstrate large-scale text reproduction.</p><p>Block printing separates authorship from scribal labor and prefigures industrial publishing.</p>",
      "timeline": "culture",
      "year": 868,
      "year_name": "",
      "year_end": 0,
      "country": [
        "CN"
      ],
      "country_name": "China",
      "hidden_tags": "print",
      "id": "e09",
      "url": "./events/e09",
      "highlight": false,
      "accuracy": false,
      "filters": [
        "rites"
      ],
      "img": "./assets/images/placeholders/e09.svg"
    },
    {
      "title": "Movable Type in East Asia",
      "intro": "<p>Ceramic and later metal type experiments show recomposable text production.</p><p>Independent inventions of movable type highlight how media breakthroughs can emerge in parallel cultures.</p>",
      "timeline": "culture",
      "year": 1040,
      "year_name": "",
      "year_end": 0,
      "country": [
        "CN"
      ],
      "country_name": "China / Korea",
      "hidden_tags": "print",
      "id": "e10",
      "url": "./events/e10",
      "highlight": false,
      "accuracy": false,
      "filters": [
        "rites"
      ],
      "img": "./assets/images/placeholders/e10.svg"
    },
    {
      "title": "Korean Hangul Promulgated",
      "intro": "<p>A new alphabet expands literacy beyond elite Classical Chinese.</p><p>Phonetic design shows media systems can be engineered.</p>",
      "timeline": "culture",
      "year": 1446,
      "year_name": "",
      "year_end": 0,
      "country": [
        "KR"
      ],
      "country_name": "Korea",
      "hidden_tags": "Korean Hangul Promulgated",
      "id": "m005",
      "url": "./events/m005",
      "highlight": false,
      "accuracy": false,
      "filters": [
        "aron",
        "arts"
      ],
      "img": "./assets/images/placeholders/m005.svg"
    },
    {
      "title": "Gutenberg Press",
      "intro": "<p>European movable-type printing scales book production and standardizes page design.</p><p>Press economics transform religion, science, and politics by collapsing the cost of identical copies.</p>",
      "timeline": "culture",
      "year": 1455,
      "year_name": "",
      "year_end": 0,
      "country": [
        "DE"
      ],
      "country_name": "Mainz",
      "hidden_tags": "print, design",
      "id": "e11",
      "url": "./events/e11",
      "highlight": false,
      "accuracy": false,
      "filters": [
        "rites",
        "arts"
      ],
      "img": "./assets/images/placeholders/e11.svg"
    },
    {
      "title": "Aldine Pocket Books",
      "intro": "<p>Portable italic editions invent reading on the move.</p><p>Format innovation reshapes who can carry a library.</p>",
      "timeline": "culture",
      "year": 1501,
      "year_name": "",
      "year_end": 0,
      "country": [
        "IT"
      ],
      "country_name": "Venice",
      "hidden_tags": "Aldine Pocket Books",
      "id": "m006",
      "url": "./events/m006",
      "highlight": false,
      "accuracy": false,
      "filters": [
        "rites",
        "arts"
      ],
      "img": "./assets/images/placeholders/m006.svg"
    },
    {
      "title": "First Newspapers",
      "intro": "<p>Periodic printed news sheets establish a cadence for public information.</p><p>Regular issues create expectation loops — audiences return for the next edition, a pattern later media inherit.</p>",
      "timeline": "highlights",
      "year": 1605,
      "year_name": "",
      "year_end": 0,
      "country": [
        "FR"
      ],
      "country_name": "Strasbourg",
      "hidden_tags": "journalism, print",
      "id": "e12",
      "url": "./events/e12",
      "highlight": false,
      "accuracy": false,
      "filters": [
        "popular",
        "rites"
      ],
      "img": "./assets/images/placeholders/e12.svg"
    },
    {
      "title": "Corantos & News Sheets",
      "intro": "<p>Weekly sheets sell foreign news to urban readers.</p><p>Periodicity trains audiences to expect updates.</p>",
      "timeline": "highlights",
      "year": 1620,
      "year_name": "",
      "year_end": 0,
      "country": [
        "NL"
      ],
      "country_name": "Amsterdam",
      "hidden_tags": "Corantos & News Sheets",
      "id": "m007",
      "url": "./events/m007",
      "highlight": false,
      "accuracy": false,
      "filters": [
        "popular",
        "rites"
      ],
      "img": "./assets/images/placeholders/m007.svg"
    },
    {
      "title": "Penny Post Concepts",
      "intro": "<p>Urban postal experiments make personal correspondence more frequent and affordable.</p><p>Cheap letters densify social graphs long before electronic messaging.</p>",
      "timeline": "lifestyle",
      "year": 1680,
      "year_name": "",
      "year_end": 0,
      "country": [
        "GB"
      ],
      "country_name": "London",
      "hidden_tags": "postal",
      "id": "e13",
      "url": "./events/e13",
      "highlight": false,
      "accuracy": false,
      "filters": [
        "hagira"
      ],
      "img": "./assets/images/placeholders/e13.svg"
    },
    {
      "title": "Spectator Essays",
      "intro": "<p>Periodical essays invent a conversational public voice.</p><p>Coffeehouse reading and print reinforce each other.</p>",
      "timeline": "highlights",
      "year": 1711,
      "year_name": "",
      "year_end": 0,
      "country": [
        "GB"
      ],
      "country_name": "London",
      "hidden_tags": "Spectator Essays",
      "id": "m008",
      "url": "./events/m008",
      "highlight": false,
      "accuracy": false,
      "filters": [
        "popular",
        "rites"
      ],
      "img": "./assets/images/placeholders/m008.svg"
    },
    {
      "title": "Encyclopédie",
      "intro": "<p>A multi-volume reference project organizes technical knowledge for a reading public.</p><p>Cross-references and plates model information architecture as a civic project.</p>",
      "timeline": "culture",
      "year": 1751,
      "year_name": "",
      "year_end": 0,
      "country": [
        "FR"
      ],
      "country_name": "Paris",
      "hidden_tags": "print, design",
      "id": "e14",
      "url": "./events/e14",
      "highlight": false,
      "accuracy": false,
      "filters": [
        "rites",
        "arts"
      ],
      "img": "./assets/images/placeholders/e14.svg"
    },
    {
      "title": "Industrial Revolution Accelerates",
      "intro": "<p>Factories and cities create demand for faster news and ads.</p>",
      "timeline": "global",
      "year": 1780,
      "year_name": "",
      "year_end": 0,
      "country": [
        "GB"
      ],
      "country_name": "Britain",
      "hidden_tags": "",
      "id": "g1780",
      "url": "./events/g1780",
      "highlight": false,
      "accuracy": false,
      "filters": [
        "surroundings"
      ],
      "img": "./assets/images/placeholders/g1780.svg"
    },
    {
      "title": "Optical Telegraph",
      "intro": "<p>Semaphore towers relay coded messages line-of-sight across long distances.</p><p>Latency drops from days to hours for state messaging — a dress rehearsal for electric networks.</p>",
      "timeline": "highlights",
      "year": 1792,
      "year_name": "",
      "year_end": 0,
      "country": [
        "FR"
      ],
      "country_name": "France",
      "hidden_tags": "telecom",
      "id": "e15",
      "url": "./events/e15",
      "highlight": false,
      "accuracy": false,
      "filters": [
        "mutual"
      ],
      "img": "./assets/images/placeholders/e15.svg"
    },
    {
      "title": "Chappe Semaphore Network",
      "intro": "<p>Optical telegraphs relay coded messages via towers.</p><p>Line-of-sight networks preview electric latency collapse.</p>",
      "timeline": "highlights",
      "year": 1794,
      "year_name": "",
      "year_end": 0,
      "country": [
        "FR"
      ],
      "country_name": "France",
      "hidden_tags": "Chappe Semaphore Network",
      "id": "m009",
      "url": "./events/m009",
      "highlight": false,
      "accuracy": false,
      "filters": [
        "mutual"
      ],
      "img": "./assets/images/placeholders/m009.svg"
    },
    {
      "title": "Lithography",
      "intro": "<p>Stone-based printing expands illustration, posters, and commercial graphics.</p><p>Artists and advertisers gain a flexible reproduction medium that fuels visual mass culture.</p>",
      "timeline": "culture",
      "year": 1796,
      "year_name": "",
      "year_end": 0,
      "country": [
        "DE"
      ],
      "country_name": "Munich",
      "hidden_tags": "print, design",
      "id": "e16",
      "url": "./events/e16",
      "highlight": false,
      "accuracy": false,
      "filters": [
        "rites",
        "arts"
      ],
      "img": "./assets/images/placeholders/e16.svg"
    },
    {
      "title": "Steam Press Speeds Newspapers",
      "intro": "<p>Mechanized presses multiply daily impression counts.</p><p>Industrial printing makes mass audiences real.</p>",
      "timeline": "culture",
      "year": 1814,
      "year_name": "",
      "year_end": 0,
      "country": [
        "GB"
      ],
      "country_name": "London",
      "hidden_tags": "Steam Press Speeds Newspapers",
      "id": "m010",
      "url": "./events/m010",
      "highlight": false,
      "accuracy": false,
      "filters": [
        "rites",
        "popular"
      ],
      "img": "./assets/images/placeholders/m010.svg"
    },
    {
      "title": "Daguerreotype",
      "intro": "<p>A practical photographic process freezes appearances with chemical fidelity.</p><p>Photography challenges drawing as the default evidence medium and invents new genres of portrait and reportage.</p>",
      "timeline": "culture",
      "year": 1839,
      "year_name": "",
      "year_end": 0,
      "country": [
        "FR"
      ],
      "country_name": "Paris",
      "hidden_tags": "photo",
      "id": "e17",
      "url": "./events/e17",
      "highlight": false,
      "accuracy": false,
      "filters": [
        "arts"
      ],
      "img": "./assets/images/placeholders/e17.svg"
    },
    {
      "title": "Postal Uniform Penny Rate",
      "intro": "<p>Rowland Hill’s reforms make distance-independent letter rates a mass service.</p><p>Stamps and prepaid postage industrialize personal and commercial correspondence.</p>",
      "timeline": "lifestyle",
      "year": 1840,
      "year_name": "",
      "year_end": 0,
      "country": [
        "GB"
      ],
      "country_name": "United Kingdom",
      "hidden_tags": "postal, social",
      "id": "e56",
      "url": "./events/e56",
      "highlight": false,
      "accuracy": false,
      "filters": [
        "hagira",
        "community"
      ],
      "img": "./assets/images/placeholders/e56.svg"
    },
    {
      "title": "Electric Telegraph",
      "intro": "<p>Morse’s line demonstrates near-instant text over wire.</p><p>Time zones, news wires, and finance sync to telegraph rhythm — distance becomes less decisive than bandwidth.</p>",
      "timeline": "highlights",
      "year": 1844,
      "year_name": "",
      "year_end": 0,
      "country": [
        "US"
      ],
      "country_name": "United States",
      "hidden_tags": "telecom",
      "id": "e18",
      "url": "./events/e18",
      "highlight": false,
      "accuracy": false,
      "filters": [
        "mutual"
      ],
      "img": "./assets/images/placeholders/e18.svg"
    },
    {
      "title": "Associated Press Wire",
      "intro": "<p>News cooperatives share telegraph reports among papers.</p><p>Wire services standardize national news tempo.</p>",
      "timeline": "highlights",
      "year": 1846,
      "year_name": "",
      "year_end": 0,
      "country": [
        "US"
      ],
      "country_name": "United States",
      "hidden_tags": "Associated Press Wire",
      "id": "m011",
      "url": "./events/m011",
      "highlight": false,
      "accuracy": false,
      "filters": [
        "popular",
        "mutual"
      ],
      "img": "./assets/images/placeholders/m011.svg"
    },
    {
      "title": "Atlantic Cable",
      "intro": "<p>A durable undersea cable links continents for message traffic.</p><p>Global news and markets begin to share a common clock, foreshadowing internet backbone geopolitics.</p>",
      "timeline": "highlights",
      "year": 1866,
      "year_name": "",
      "year_end": 0,
      "country": [
        "US"
      ],
      "country_name": "Atlantic",
      "hidden_tags": "telecom, network",
      "id": "e19",
      "url": "./events/e19",
      "highlight": false,
      "accuracy": false,
      "filters": [
        "mutual",
        "gender"
      ],
      "img": "./assets/images/placeholders/e19.svg"
    },
    {
      "title": "Typewriter Standardizes",
      "intro": "<p>Commercial typewriters normalize office text production and QWERTY layouts.</p><p>Mechanical keyboards reshape literacy labor and later influence computer input design.</p>",
      "timeline": "culture",
      "year": 1874,
      "year_name": "",
      "year_end": 0,
      "country": [
        "US"
      ],
      "country_name": "United States",
      "hidden_tags": "writing, design",
      "id": "e20",
      "url": "./events/e20",
      "highlight": false,
      "accuracy": false,
      "filters": [
        "aron",
        "arts"
      ],
      "img": "./assets/images/placeholders/e20.svg"
    },
    {
      "title": "Telephone Patent Era",
      "intro": "<p>Voice carried electrically opens conversational distance-collapse.</p><p>Switchboards and directories invent real-time interpersonal media as infrastructure.</p>",
      "timeline": "highlights",
      "year": 1876,
      "year_name": "",
      "year_end": 0,
      "country": [
        "US"
      ],
      "country_name": "United States",
      "hidden_tags": "telecom, audio",
      "id": "e21",
      "url": "./events/e21",
      "highlight": false,
      "accuracy": false,
      "filters": [
        "mutual",
        "circle-of-life"
      ],
      "img": "./assets/images/placeholders/e21.svg"
    },
    {
      "title": "Phonograph",
      "intro": "<p>Recorded sound becomes storable and replayable outside live performance.</p><p>Music, speech, and later radio content gain a durable medium independent of performers.</p>",
      "timeline": "lifestyle",
      "year": 1877,
      "year_name": "",
      "year_end": 0,
      "country": [
        "US"
      ],
      "country_name": "United States",
      "hidden_tags": "audio",
      "id": "e22",
      "url": "./events/e22",
      "highlight": false,
      "accuracy": false,
      "filters": [
        "circle-of-life"
      ],
      "img": "./assets/images/placeholders/e22.svg"
    },
    {
      "title": "Kodak Snapshot Culture",
      "intro": "<p>Simple cameras and processing services democratize personal image-making.</p><p>Everyday photography shifts from specialist craft to household habit.</p>",
      "timeline": "culture",
      "year": 1888,
      "year_name": "",
      "year_end": 0,
      "country": [
        "US"
      ],
      "country_name": "United States",
      "hidden_tags": "photo, social",
      "id": "e23",
      "url": "./events/e23",
      "highlight": false,
      "accuracy": false,
      "filters": [
        "arts",
        "community"
      ],
      "img": "./assets/images/placeholders/e23.svg"
    },
    {
      "title": "Cinema Projection",
      "intro": "<p>Public film screenings establish moving images as shared spectacle.</p><p>Theaters become ritual spaces for collective attention — a template for later screening cultures.</p>",
      "timeline": "culture",
      "year": 1895,
      "year_name": "",
      "year_end": 0,
      "country": [
        "FR"
      ],
      "country_name": "Paris",
      "hidden_tags": "photo, broadcast",
      "id": "e24",
      "url": "./events/e24",
      "highlight": false,
      "accuracy": false,
      "filters": [
        "arts",
        "zionism"
      ],
      "img": "./assets/images/placeholders/e24.svg"
    },
    {
      "title": "Kodak Brownie",
      "intro": "<p>Ultra-cheap cameras push snapshots into everyday life.</p><p>Amateur photography scales into a mass habit.</p>",
      "timeline": "culture",
      "year": 1900,
      "year_name": "",
      "year_end": 0,
      "country": [
        "US"
      ],
      "country_name": "United States",
      "hidden_tags": "Kodak Brownie",
      "id": "m012",
      "url": "./events/m012",
      "highlight": false,
      "accuracy": false,
      "filters": [
        "arts",
        "community"
      ],
      "img": "./assets/images/placeholders/m012.svg"
    },
    {
      "title": "Marconi Wireless",
      "intro": "<p>Transatlantic wireless signals prove radio as a message medium.</p><p>Untethered transmission enables maritime safety, news flashes, and eventually entertainment broadcasting.</p>",
      "timeline": "highlights",
      "year": 1901,
      "year_name": "",
      "year_end": 0,
      "country": [
        "US"
      ],
      "country_name": "Atlantic",
      "hidden_tags": "telecom, broadcast",
      "id": "e25",
      "url": "./events/e25",
      "highlight": false,
      "accuracy": false,
      "filters": [
        "mutual",
        "zionism"
      ],
      "img": "./assets/images/placeholders/e25.svg"
    },
    {
      "title": "Offset Printing Industrializes",
      "intro": "<p>Offset lithography accelerates high-volume commercial print.</p><p>Magazines, packaging, and advertising gain cheaper, sharper color reproduction.</p>",
      "timeline": "culture",
      "year": 1904,
      "year_name": "",
      "year_end": 0,
      "country": [
        "US"
      ],
      "country_name": "United States",
      "hidden_tags": "print, design",
      "id": "e57",
      "url": "./events/e57",
      "highlight": false,
      "accuracy": false,
      "filters": [
        "rites",
        "arts"
      ],
      "img": "./assets/images/placeholders/e57.svg"
    },
    {
      "title": "Halftone Newspapers",
      "intro": "<p>Photographic halftones become routine in mass newspapers.</p><p>Visual evidence enters daily news cycles, changing what counts as a story.</p>",
      "timeline": "highlights",
      "year": 1905,
      "year_name": "",
      "year_end": 0,
      "country": [
        "US"
      ],
      "country_name": "Global press",
      "hidden_tags": "journalism, print, photo",
      "id": "e26",
      "url": "./events/e26",
      "highlight": false,
      "accuracy": false,
      "filters": [
        "popular",
        "rites",
        "arts"
      ],
      "img": "./assets/images/placeholders/e26.svg"
    },
    {
      "title": "World Wars Remake Propaganda",
      "intro": "<p>States mobilize film, radio, and posters at unprecedented scale.</p>",
      "timeline": "global",
      "year": 1914,
      "year_name": "",
      "year_end": 0,
      "country": [
        "US"
      ],
      "country_name": "Global",
      "hidden_tags": "",
      "id": "g1914",
      "url": "./events/g1914",
      "highlight": false,
      "accuracy": false,
      "filters": [
        "surroundings"
      ],
      "img": "./assets/images/placeholders/g1914.svg"
    },
    {
      "title": "Commercial Radio Boom",
      "intro": "<p>Scheduled radio programming builds national audiences in real time.</p><p>Advertising-supported broadcasting invents appointment listening and shared sonic culture.</p>",
      "timeline": "highlights",
      "year": 1920,
      "year_name": "",
      "year_end": 0,
      "country": [
        "US"
      ],
      "country_name": "United States",
      "hidden_tags": "broadcast, audio",
      "id": "e27",
      "url": "./events/e27",
      "highlight": false,
      "accuracy": false,
      "filters": [
        "zionism",
        "circle-of-life"
      ],
      "img": "./assets/images/placeholders/e27.svg"
    },
    {
      "title": "BBC Radio Service",
      "intro": "<p>National radio schedules create shared listening hours.</p><p>Public broadcasting defines civic sonic space.</p>",
      "timeline": "highlights",
      "year": 1922,
      "year_name": "",
      "year_end": 0,
      "country": [
        "GB"
      ],
      "country_name": "United Kingdom",
      "hidden_tags": "BBC Radio Service",
      "id": "m013",
      "url": "./events/m013",
      "highlight": false,
      "accuracy": false,
      "filters": [
        "zionism",
        "circle-of-life"
      ],
      "img": "./assets/images/placeholders/m013.svg"
    },
    {
      "title": "Talking Pictures",
      "intro": "<p>Synchronized sound transforms cinema storytelling and industry structure.</p><p>Studios retool for dialogue, music scoring, and new star systems built on voice.</p>",
      "timeline": "culture",
      "year": 1927,
      "year_name": "",
      "year_end": 0,
      "country": [
        "US"
      ],
      "country_name": "United States",
      "hidden_tags": "photo, audio",
      "id": "e28",
      "url": "./events/e28",
      "highlight": false,
      "accuracy": false,
      "filters": [
        "arts",
        "circle-of-life"
      ],
      "img": "./assets/images/placeholders/e28.svg"
    },
    {
      "title": "Talkies Go Mainstream",
      "intro": "<p>Synchronized sound remakes film studios and stardom.</p><p>Cinema becomes audiovisual by default.</p>",
      "timeline": "culture",
      "year": 1929,
      "year_name": "",
      "year_end": 0,
      "country": [
        "US"
      ],
      "country_name": "United States",
      "hidden_tags": "Talkies Go Mainstream",
      "id": "m014",
      "url": "./events/m014",
      "highlight": false,
      "accuracy": false,
      "filters": [
        "arts",
        "circle-of-life"
      ],
      "img": "./assets/images/placeholders/m014.svg"
    },
    {
      "title": "Television Experiments to Sets",
      "intro": "<p>Regular television service begins to move images into the home.</p><p>Living-room screens relocate public spectacle into domestic schedules.</p>",
      "timeline": "highlights",
      "year": 1936,
      "year_name": "",
      "year_end": 0,
      "country": [
        "GB"
      ],
      "country_name": "United Kingdom",
      "hidden_tags": "broadcast",
      "id": "e29",
      "url": "./events/e29",
      "highlight": false,
      "accuracy": false,
      "filters": [
        "zionism"
      ],
      "img": "./assets/images/placeholders/e29.svg"
    },
    {
      "title": "Magnetic Tape Recording",
      "intro": "<p>High-quality tape enables editing, delay, and studio production workflows.</p><p>Broadcast and music industries gain non-linear control over recorded time.</p>",
      "timeline": "lifestyle",
      "year": 1940,
      "year_name": "",
      "year_end": 0,
      "country": [
        "DE"
      ],
      "country_name": "Germany / US",
      "hidden_tags": "audio, broadcast",
      "id": "e30",
      "url": "./events/e30",
      "highlight": false,
      "accuracy": false,
      "filters": [
        "circle-of-life",
        "zionism"
      ],
      "img": "./assets/images/placeholders/e30.svg"
    },
    {
      "title": "ENIAC & Stored Programs",
      "intro": "<p>Electronic computation accelerates and soon stores instructions as data.</p><p>Programmable machines become a new medium for symbols — not only calculation tools.</p>",
      "timeline": "highlights",
      "year": 1945,
      "year_name": "",
      "year_end": 0,
      "country": [
        "US"
      ],
      "country_name": "United States",
      "hidden_tags": "compute",
      "id": "e31",
      "url": "./events/e31",
      "highlight": false,
      "accuracy": false,
      "filters": [
        "discoveries"
      ],
      "img": "./assets/images/placeholders/e31.svg"
    },
    {
      "title": "Transistor Radio",
      "intro": "<p>Portable radios detach listening from furniture and family rooms.</p><p>Youth culture and mobile attention patterns intensify with pocket receivers.</p>",
      "timeline": "highlights",
      "year": 1954,
      "year_name": "",
      "year_end": 0,
      "country": [
        "US"
      ],
      "country_name": "United States",
      "hidden_tags": "broadcast, audio",
      "id": "e32",
      "url": "./events/e32",
      "highlight": false,
      "accuracy": false,
      "filters": [
        "zionism",
        "circle-of-life"
      ],
      "img": "./assets/images/placeholders/e32.svg"
    },
    {
      "title": "Cold War Broadcast Rivalry",
      "intro": "<p>Shortwave and television become geopolitical stages.</p>",
      "timeline": "global",
      "year": 1955,
      "year_name": "",
      "year_end": 0,
      "country": [
        "US"
      ],
      "country_name": "Global",
      "hidden_tags": "",
      "id": "g1955",
      "url": "./events/g1955",
      "highlight": false,
      "accuracy": false,
      "filters": [
        "surroundings"
      ],
      "img": "./assets/images/placeholders/g1955.svg"
    },
    {
      "title": "Helvetica & Modernist UI Roots",
      "intro": "<p>Neutral sans-serif type becomes a global interface for clarity.</p><p>Corporate identity and later screen UI borrow modernist typographic neutrality.</p>",
      "timeline": "culture",
      "year": 1957,
      "year_name": "",
      "year_end": 0,
      "country": [
        "CH"
      ],
      "country_name": "Switzerland",
      "hidden_tags": "design",
      "id": "e58",
      "url": "./events/e58",
      "highlight": false,
      "accuracy": false,
      "filters": [
        "arts"
      ],
      "img": "./assets/images/placeholders/e58.svg"
    },
    {
      "title": "TV News as Ritual",
      "intro": "<p>Televised debates and evening news consolidate visual politics.</p><p>Image performance becomes inseparable from electoral and wartime narration.</p>",
      "timeline": "highlights",
      "year": 1960,
      "year_name": "",
      "year_end": 0,
      "country": [
        "US"
      ],
      "country_name": "United States",
      "hidden_tags": "broadcast, journalism",
      "id": "e33",
      "url": "./events/e33",
      "highlight": false,
      "accuracy": false,
      "filters": [
        "zionism",
        "popular"
      ],
      "img": "./assets/images/placeholders/e33.svg"
    },
    {
      "title": "Satellite TV & Global Feeds",
      "intro": "<p>Telstar and successors relay live television across oceans.</p><p>Audiences experience simultaneous planetary events — a new scale of shared media time.</p>",
      "timeline": "highlights",
      "year": 1962,
      "year_name": "",
      "year_end": 0,
      "country": [
        "US"
      ],
      "country_name": "Orbit / Atlantic",
      "hidden_tags": "broadcast, telecom",
      "id": "e59",
      "url": "./events/e59",
      "highlight": false,
      "accuracy": false,
      "filters": [
        "zionism",
        "mutual"
      ],
      "img": "./assets/images/placeholders/e59.svg"
    },
    {
      "title": "Telstar Live Relay",
      "intro": "<p>Satellite hops send live TV across the Atlantic.</p><p>Planetary simultaneity becomes a media genre.</p>",
      "timeline": "highlights",
      "year": 1962,
      "year_name": "",
      "year_end": 0,
      "country": [
        "US"
      ],
      "country_name": "Orbit",
      "hidden_tags": "Telstar Live Relay",
      "id": "m015",
      "url": "./events/m015",
      "highlight": false,
      "accuracy": false,
      "filters": [
        "zionism",
        "mutual"
      ],
      "img": "./assets/images/placeholders/m015.svg"
    },
    {
      "title": "Compact Cassette Popularizes",
      "intro": "<p>Tape cassettes make recording and mixtapes personal.</p><p>Consumers gain write-access to audio media.</p>",
      "timeline": "lifestyle",
      "year": 1963,
      "year_name": "",
      "year_end": 0,
      "country": [
        "NL"
      ],
      "country_name": "Netherlands",
      "hidden_tags": "Compact Cassette Popularizes",
      "id": "m016",
      "url": "./events/m016",
      "highlight": false,
      "accuracy": false,
      "filters": [
        "circle-of-life"
      ],
      "img": "./assets/images/placeholders/m016.svg"
    },
    {
      "title": "Packet Switching Ideas",
      "intro": "<p>Researchers propose breaking messages into routed packets.</p><p>Resilient data networks replace circuit assumptions and enable the internet stack.</p>",
      "timeline": "highlights",
      "year": 1964,
      "year_name": "",
      "year_end": 0,
      "country": [
        "US"
      ],
      "country_name": "UK / US",
      "hidden_tags": "network, compute",
      "id": "e34",
      "url": "./events/e34",
      "highlight": false,
      "accuracy": false,
      "filters": [
        "gender",
        "discoveries"
      ],
      "img": "./assets/images/placeholders/e34.svg"
    },
    {
      "title": "ARPANET First Link",
      "intro": "<p>Host-to-host networking begins among research institutions.</p><p>Email and file transfer soon show that networks are social media before the brand exists.</p>",
      "timeline": "highlights",
      "year": 1969,
      "year_name": "",
      "year_end": 0,
      "country": [
        "US"
      ],
      "country_name": "United States",
      "hidden_tags": "network",
      "id": "e35",
      "url": "./events/e35",
      "highlight": false,
      "accuracy": false,
      "filters": [
        "gender"
      ],
      "img": "./assets/images/placeholders/e35.svg"
    },
    {
      "title": "Color TV Saturation",
      "intro": "<p>Color broadcasting becomes mainstream in many markets.</p><p>Chromatic realism raises production values and advertising spectacle.</p>",
      "timeline": "highlights",
      "year": 1972,
      "year_name": "",
      "year_end": 0,
      "country": [
        "US"
      ],
      "country_name": "Global",
      "hidden_tags": "broadcast",
      "id": "e36",
      "url": "./events/e36",
      "highlight": false,
      "accuracy": false,
      "filters": [
        "zionism"
      ],
      "img": "./assets/images/placeholders/e36.svg"
    },
    {
      "title": "Pong & Arcade Screens",
      "intro": "<p>Interactive screens become entertainment machines.</p><p>Games invent a new audiovisual literacy.</p>",
      "timeline": "highlights",
      "year": 1972,
      "year_name": "",
      "year_end": 0,
      "country": [
        "US"
      ],
      "country_name": "United States",
      "hidden_tags": "Pong & Arcade Screens",
      "id": "m017",
      "url": "./events/m017",
      "highlight": false,
      "accuracy": false,
      "filters": [
        "discoveries"
      ],
      "img": "./assets/images/placeholders/m017.svg"
    },
    {
      "title": "Personal Computing Arrives",
      "intro": "<p>Home computers put interactive screens in non-institutional spaces.</p><p>Hobbyists, schools, and offices invent new literacies around software as medium.</p>",
      "timeline": "highlights",
      "year": 1977,
      "year_name": "",
      "year_end": 0,
      "country": [
        "US"
      ],
      "country_name": "United States",
      "hidden_tags": "compute, design",
      "id": "e37",
      "url": "./events/e37",
      "highlight": false,
      "accuracy": false,
      "filters": [
        "discoveries",
        "arts"
      ],
      "img": "./assets/images/placeholders/e37.svg"
    },
    {
      "title": "Walkman & Private Soundtrack",
      "intro": "<p>Personal cassette players privatize public space with headphones.</p><p>Mobile listening cultures redefine urban attention and later earbud norms.</p>",
      "timeline": "lifestyle",
      "year": 1979,
      "year_name": "",
      "year_end": 0,
      "country": [
        "JP"
      ],
      "country_name": "Japan",
      "hidden_tags": "audio, social",
      "id": "e38",
      "url": "./events/e38",
      "highlight": false,
      "accuracy": false,
      "filters": [
        "circle-of-life",
        "community"
      ],
      "img": "./assets/images/placeholders/e38.svg"
    },
    {
      "title": "CNN 24-Hour News",
      "intro": "<p>Continuous TV news invents a never-ending cycle.</p><p>Liveness and repetition redefine urgency.</p>",
      "timeline": "highlights",
      "year": 1980,
      "year_name": "",
      "year_end": 0,
      "country": [
        "US"
      ],
      "country_name": "United States",
      "hidden_tags": "CNN 24-Hour News",
      "id": "m018",
      "url": "./events/m018",
      "highlight": false,
      "accuracy": false,
      "filters": [
        "zionism",
        "popular"
      ],
      "img": "./assets/images/placeholders/m018.svg"
    },
    {
      "title": "CD Digital Audio",
      "intro": "<p>Optical discs standardize consumer digital sound distribution.</p><p>Perfect-copy audio shifts industry economics and listener expectations of fidelity.</p>",
      "timeline": "lifestyle",
      "year": 1982,
      "year_name": "",
      "year_end": 0,
      "country": [
        "JP"
      ],
      "country_name": "Japan / Netherlands",
      "hidden_tags": "audio",
      "id": "e40",
      "url": "./events/e40",
      "highlight": false,
      "accuracy": false,
      "filters": [
        "circle-of-life"
      ],
      "img": "./assets/images/placeholders/e40.svg"
    },
    {
      "title": "MIDI Music Protocol",
      "intro": "<p>Instruments and computers share a control language.</p><p>Electronic music production becomes modular.</p>",
      "timeline": "lifestyle",
      "year": 1983,
      "year_name": "",
      "year_end": 0,
      "country": [
        "JP"
      ],
      "country_name": "Global",
      "hidden_tags": "MIDI Music Protocol",
      "id": "m019",
      "url": "./events/m019",
      "highlight": false,
      "accuracy": false,
      "filters": [
        "circle-of-life",
        "discoveries"
      ],
      "img": "./assets/images/placeholders/m019.svg"
    },
    {
      "title": "GUI & Desktop Metaphor",
      "intro": "<p>Graphical interfaces popularize windows, icons, and direct manipulation.</p><p>Visual computing becomes the default language for personal media tools.</p>",
      "timeline": "highlights",
      "year": 1984,
      "year_name": "",
      "year_end": 0,
      "country": [
        "US"
      ],
      "country_name": "United States",
      "hidden_tags": "compute, design",
      "id": "e39",
      "url": "./events/e39",
      "highlight": false,
      "accuracy": false,
      "filters": [
        "discoveries",
        "arts"
      ],
      "img": "./assets/images/placeholders/e39.svg"
    },
    {
      "title": "Fiber Optic Backbones",
      "intro": "<p>Glass fibers carry enormous bandwidth for voice and data.</p><p>Undersea and terrestrial fiber become the quiet substrate of modern platforms.</p>",
      "timeline": "highlights",
      "year": 1988,
      "year_name": "",
      "year_end": 0,
      "country": [
        "US"
      ],
      "country_name": "Global",
      "hidden_tags": "telecom, network",
      "id": "e60",
      "url": "./events/e60",
      "highlight": false,
      "accuracy": false,
      "filters": [
        "mutual",
        "gender"
      ],
      "img": "./assets/images/placeholders/e60.svg"
    },
    {
      "title": "Open Source Collaboration",
      "intro": "<p>Publicly shared codebases coordinate distributed development.</p><p>Version control and mailing lists invent durable patterns for remote creative work.</p>",
      "timeline": "highlights",
      "year": 1991,
      "year_name": "",
      "year_end": 0,
      "country": [
        "US"
      ],
      "country_name": "Global",
      "hidden_tags": "compute, network",
      "id": "e61",
      "url": "./events/e61",
      "highlight": false,
      "accuracy": false,
      "filters": [
        "discoveries",
        "gender"
      ],
      "img": "./assets/images/placeholders/e61.svg"
    },
    {
      "title": "World Wide Web",
      "intro": "<p>Hypertext over internet protocols makes linked documents universal.</p><p>Browsers turn the network into a publishable medium anyone can address by URL.</p>",
      "timeline": "highlights",
      "year": 1991,
      "year_name": "",
      "year_end": 0,
      "country": [
        "CH"
      ],
      "country_name": "CERN",
      "hidden_tags": "network, journalism",
      "id": "e41",
      "url": "./events/e41",
      "highlight": false,
      "accuracy": false,
      "filters": [
        "gender",
        "popular"
      ],
      "img": "./assets/images/placeholders/e41.svg"
    },
    {
      "title": "SMS Texting Culture",
      "intro": "<p>Short messages become a mass interpersonal channel on mobiles.</p><p>Character limits invent new slang, timing norms, and always-on social presence.</p>",
      "timeline": "highlights",
      "year": 1993,
      "year_name": "",
      "year_end": 0,
      "country": [
        "DE"
      ],
      "country_name": "Europe",
      "hidden_tags": "telecom, social",
      "id": "e42",
      "url": "./events/e42",
      "highlight": false,
      "accuracy": false,
      "filters": [
        "mutual",
        "community"
      ],
      "img": "./assets/images/placeholders/e42.svg"
    },
    {
      "title": "Digital Cameras Consumerize",
      "intro": "<p>Filmless cameras make instant review and deletion normal.</p><p>Zero marginal cost per shot changes photographic selectivity and volume.</p>",
      "timeline": "culture",
      "year": 1995,
      "year_name": "",
      "year_end": 0,
      "country": [
        "JP"
      ],
      "country_name": "Japan / Global",
      "hidden_tags": "photo",
      "id": "e62",
      "url": "./events/e62",
      "highlight": false,
      "accuracy": false,
      "filters": [
        "arts"
      ],
      "img": "./assets/images/placeholders/e62.svg"
    },
    {
      "title": "Netscape IPO & Web Boom",
      "intro": "<p>Browsers make the web a mass consumer medium.</p><p>Hyperlinks become default navigation grammar.</p>",
      "timeline": "highlights",
      "year": 1995,
      "year_name": "",
      "year_end": 0,
      "country": [
        "US"
      ],
      "country_name": "United States",
      "hidden_tags": "Netscape IPO & Web Boom",
      "id": "m020",
      "url": "./events/m020",
      "highlight": false,
      "accuracy": false,
      "filters": [
        "gender"
      ],
      "img": "./assets/images/placeholders/m020.svg"
    },
    {
      "title": "Global Internet Backbone Boom",
      "intro": "<p>Fiber and IXPs turn networks into planetary media substrate.</p>",
      "timeline": "global",
      "year": 1998,
      "year_name": "",
      "year_end": 0,
      "country": [
        "US"
      ],
      "country_name": "Global",
      "hidden_tags": "",
      "id": "g1998",
      "url": "./events/g1998",
      "highlight": false,
      "accuracy": false,
      "filters": [
        "surroundings"
      ],
      "img": "./assets/images/placeholders/g1998.svg"
    },
    {
      "title": "Google Search Scales",
      "intro": "<p>Ranking algorithms become the web’s front door.</p><p>Discoverability outranks mere publishing.</p>",
      "timeline": "highlights",
      "year": 1998,
      "year_name": "",
      "year_end": 0,
      "country": [
        "US"
      ],
      "country_name": "United States",
      "hidden_tags": "Google Search Scales",
      "id": "m021",
      "url": "./events/m021",
      "highlight": false,
      "accuracy": false,
      "filters": [
        "gender",
        "popular"
      ],
      "img": "./assets/images/placeholders/m021.svg"
    },
    {
      "title": "Search Engines Scale",
      "intro": "<p>Algorithmic ranking becomes the front door to the web’s archive.</p><p>Discoverability — not just publishing — becomes the scarce media resource.</p>",
      "timeline": "highlights",
      "year": 1998,
      "year_name": "",
      "year_end": 0,
      "country": [
        "US"
      ],
      "country_name": "United States",
      "hidden_tags": "network, journalism",
      "id": "e43",
      "url": "./events/e43",
      "highlight": false,
      "accuracy": false,
      "filters": [
        "gender",
        "popular"
      ],
      "img": "./assets/images/placeholders/e43.svg"
    },
    {
      "title": "Blogging Platforms",
      "intro": "<p>Easy publishing tools expand who can maintain a public chronicle.</p><p>Reverse-chronological feeds prefigure later social streams and creator economies.</p>",
      "timeline": "lifestyle",
      "year": 1999,
      "year_name": "",
      "year_end": 0,
      "country": [
        "US"
      ],
      "country_name": "Global",
      "hidden_tags": "social, journalism",
      "id": "e44",
      "url": "./events/e44",
      "highlight": false,
      "accuracy": false,
      "filters": [
        "community",
        "popular"
      ],
      "img": "./assets/images/placeholders/e44.svg"
    },
    {
      "title": "Wikipedia",
      "intro": "<p>Collaborative encyclopedias show peer production at planetary scale.</p><p>Version history and citation norms become visible infrastructure for contested facts.</p>",
      "timeline": "highlights",
      "year": 2001,
      "year_name": "",
      "year_end": 0,
      "country": [
        "US"
      ],
      "country_name": "Global",
      "hidden_tags": "network, writing",
      "id": "e45",
      "url": "./events/e45",
      "highlight": false,
      "accuracy": false,
      "filters": [
        "gender",
        "aron"
      ],
      "img": "./assets/images/placeholders/e45.svg"
    },
    {
      "title": "Wikipedia Launches",
      "intro": "<p>Collaborative encyclopedias scale peer production.</p><p>Version history makes knowledge contested.</p>",
      "timeline": "highlights",
      "year": 2001,
      "year_name": "",
      "year_end": 0,
      "country": [
        "US"
      ],
      "country_name": "Global",
      "hidden_tags": "Wikipedia Launches",
      "id": "m022",
      "url": "./events/m022",
      "highlight": false,
      "accuracy": false,
      "filters": [
        "gender",
        "aron"
      ],
      "img": "./assets/images/placeholders/m022.svg"
    },
    {
      "title": "RSS & Syndicated Feeds",
      "intro": "<p>Machine-readable feeds let readers pull updates from many publishers.</p><p>Syndication decouples publishing from a single homepage destination.</p>",
      "timeline": "highlights",
      "year": 2002,
      "year_name": "",
      "year_end": 0,
      "country": [
        "US"
      ],
      "country_name": "Web",
      "hidden_tags": "journalism, network",
      "id": "e63",
      "url": "./events/e63",
      "highlight": false,
      "accuracy": false,
      "filters": [
        "popular",
        "gender"
      ],
      "img": "./assets/images/placeholders/e63.svg"
    },
    {
      "title": "Social Networks Mainstream",
      "intro": "<p>Profile-based networks organize identity, friendship, and attention graphs.</p><p>The feed becomes a primary interface to news, culture, and personal performance.</p>",
      "timeline": "lifestyle",
      "year": 2004,
      "year_name": "",
      "year_end": 0,
      "country": [
        "US"
      ],
      "country_name": "United States",
      "hidden_tags": "social, network",
      "id": "e46",
      "url": "./events/e46",
      "highlight": false,
      "accuracy": false,
      "filters": [
        "community",
        "gender"
      ],
      "img": "./assets/images/placeholders/e46.svg"
    },
    {
      "title": "YouTube & Video Upload",
      "intro": "<p>Amateur video distribution scales without broadcast gatekeepers.</p><p>On-demand clips invent new genres, virality mechanics, and creator livelihoods.</p>",
      "timeline": "highlights",
      "year": 2005,
      "year_name": "",
      "year_end": 0,
      "country": [
        "US"
      ],
      "country_name": "United States",
      "hidden_tags": "broadcast, social, photo",
      "id": "e47",
      "url": "./events/e47",
      "highlight": false,
      "accuracy": false,
      "filters": [
        "zionism",
        "community",
        "arts"
      ],
      "img": "./assets/images/placeholders/e47.svg"
    },
    {
      "title": "Facebook Opens Broadly",
      "intro": "<p>Profile graphs become a mainstream social interface.</p><p>The feed consolidates identity and news.</p>",
      "timeline": "lifestyle",
      "year": 2006,
      "year_name": "",
      "year_end": 0,
      "country": [
        "US"
      ],
      "country_name": "United States",
      "hidden_tags": "Facebook Opens Broadly",
      "id": "m023",
      "url": "./events/m023",
      "highlight": false,
      "accuracy": false,
      "filters": [
        "community",
        "gender"
      ],
      "img": "./assets/images/placeholders/m023.svg"
    },
    {
      "title": "Smartphone Convergence",
      "intro": "<p>Phones absorb camera, browser, music player, and messaging into one slab.</p><p>Always-carried computers make media capture and consumption continuous.</p>",
      "timeline": "highlights",
      "year": 2007,
      "year_name": "",
      "year_end": 0,
      "country": [
        "US"
      ],
      "country_name": "United States",
      "hidden_tags": "telecom, compute, photo",
      "id": "e48",
      "url": "./events/e48",
      "highlight": false,
      "accuracy": false,
      "filters": [
        "mutual",
        "discoveries",
        "arts"
      ],
      "img": "./assets/images/placeholders/e48.svg"
    },
    {
      "title": "App Stores & Push Feeds",
      "intro": "<p>Curated software marketplaces and notifications reorganize attention.</p><p>Distribution shifts from open web surfing to gated, interrupt-driven apps.</p>",
      "timeline": "highlights",
      "year": 2008,
      "year_name": "",
      "year_end": 0,
      "country": [
        "US"
      ],
      "country_name": "Global",
      "hidden_tags": "network, social",
      "id": "e49",
      "url": "./events/e49",
      "highlight": false,
      "accuracy": false,
      "filters": [
        "gender",
        "community"
      ],
      "img": "./assets/images/placeholders/e49.svg"
    },
    {
      "title": "iPhone App Ecosystem",
      "intro": "<p>Touch apps replace many single-purpose media devices.</p><p>Notifications invent interrupt-driven attention.</p>",
      "timeline": "highlights",
      "year": 2008,
      "year_name": "",
      "year_end": 0,
      "country": [
        "US"
      ],
      "country_name": "United States",
      "hidden_tags": "iPhone App Ecosystem",
      "id": "m024",
      "url": "./events/m024",
      "highlight": false,
      "accuracy": false,
      "filters": [
        "mutual",
        "discoveries",
        "gender"
      ],
      "img": "./assets/images/placeholders/m024.svg"
    },
    {
      "title": "Cloud Media Libraries",
      "intro": "<p>Personal archives migrate to remote storage synced across devices.</p><p>Access replaces possession as the everyday metaphor for media collections.</p>",
      "timeline": "highlights",
      "year": 2010,
      "year_name": "",
      "year_end": 0,
      "country": [
        "US"
      ],
      "country_name": "Global",
      "hidden_tags": "network, photo, audio",
      "id": "e64",
      "url": "./events/e64",
      "highlight": false,
      "accuracy": false,
      "filters": [
        "gender",
        "arts",
        "circle-of-life"
      ],
      "img": "./assets/images/placeholders/e64.svg"
    },
    {
      "title": "Instagram Visual Feed",
      "intro": "<p>Filters invent a new everyday camera culture.</p><p>Visual status updates accelerate mobile photography.</p>",
      "timeline": "lifestyle",
      "year": 2010,
      "year_name": "",
      "year_end": 0,
      "country": [
        "US"
      ],
      "country_name": "United States",
      "hidden_tags": "Instagram Visual Feed",
      "id": "m025",
      "url": "./events/m025",
      "highlight": false,
      "accuracy": false,
      "filters": [
        "community",
        "arts"
      ],
      "img": "./assets/images/placeholders/m025.svg"
    },
    {
      "title": "Streaming Music Norm",
      "intro": "<p>Subscription catalogs replace ownership as the default listening model.</p><p>Recommendation systems become co-authors of taste and chart dynamics.</p>",
      "timeline": "lifestyle",
      "year": 2011,
      "year_name": "",
      "year_end": 0,
      "country": [
        "US"
      ],
      "country_name": "Global",
      "hidden_tags": "audio, network",
      "id": "e50",
      "url": "./events/e50",
      "highlight": false,
      "accuracy": false,
      "filters": [
        "circle-of-life",
        "gender"
      ],
      "img": "./assets/images/placeholders/e50.svg"
    },
    {
      "title": "Mobile-First News",
      "intro": "<p>Cards, snaps, and vertical video reshape how stories are packaged.</p><p>Newsrooms redesign for thumb-stopping formats and platform referral traffic.</p>",
      "timeline": "highlights",
      "year": 2013,
      "year_name": "",
      "year_end": 0,
      "country": [
        "US"
      ],
      "country_name": "Global",
      "hidden_tags": "journalism, social",
      "id": "e51",
      "url": "./events/e51",
      "highlight": false,
      "accuracy": false,
      "filters": [
        "popular",
        "community"
      ],
      "img": "./assets/images/placeholders/e51.svg"
    },
    {
      "title": "Live Streaming Everywhere",
      "intro": "<p>Anyone can broadcast live from a pocket camera to global audiences.</p><p>Liveness returns as a participatory format spanning games, protests, and performance.</p>",
      "timeline": "highlights",
      "year": 2016,
      "year_name": "",
      "year_end": 0,
      "country": [
        "US"
      ],
      "country_name": "Global",
      "hidden_tags": "broadcast, social",
      "id": "e52",
      "url": "./events/e52",
      "highlight": false,
      "accuracy": false,
      "filters": [
        "zionism",
        "community"
      ],
      "img": "./assets/images/placeholders/e52.svg"
    },
    {
      "title": "Podcast Renaissance",
      "intro": "<p>On-demand spoken audio becomes a major narrative and news medium.</p><p>Long-form listening thrives alongside short video, showing format diversity in networked eras.</p>",
      "timeline": "lifestyle",
      "year": 2018,
      "year_name": "",
      "year_end": 0,
      "country": [
        "US"
      ],
      "country_name": "Global",
      "hidden_tags": "audio, journalism",
      "id": "e53",
      "url": "./events/e53",
      "highlight": false,
      "accuracy": false,
      "filters": [
        "circle-of-life",
        "popular"
      ],
      "img": "./assets/images/placeholders/e53.svg"
    },
    {
      "title": "TikTok Global Rise",
      "intro": "<p>Algorithmic short video dominates youth attention.</p><p>For You feeds displace follower-graph discovery.</p>",
      "timeline": "lifestyle",
      "year": 2018,
      "year_name": "",
      "year_end": 0,
      "country": [
        "CN"
      ],
      "country_name": "Global",
      "hidden_tags": "TikTok Global Rise",
      "id": "m026",
      "url": "./events/m026",
      "highlight": false,
      "accuracy": false,
      "filters": [
        "community",
        "arts",
        "zionism"
      ],
      "img": "./assets/images/placeholders/m026.svg"
    },
    {
      "title": "Short-Form Video Dominance",
      "intro": "<p>Vertical looping clips capture massive share of youth attention.</p><p>Algorithmic For You feeds intensify discovery without follower graphs.</p>",
      "timeline": "lifestyle",
      "year": 2020,
      "year_name": "",
      "year_end": 0,
      "country": [
        "US"
      ],
      "country_name": "Global",
      "hidden_tags": "social, photo, broadcast",
      "id": "e54",
      "url": "./events/e54",
      "highlight": false,
      "accuracy": false,
      "filters": [
        "community",
        "arts",
        "zionism"
      ],
      "img": "./assets/images/placeholders/e54.svg"
    },
    {
      "title": "AI Image Generators Public",
      "intro": "<p>Text-to-image tools flood creative workflows.</p><p>Provenance and authorship become urgent problems.</p>",
      "timeline": "highlights",
      "year": 2022,
      "year_name": "",
      "year_end": 0,
      "country": [
        "US"
      ],
      "country_name": "Global",
      "hidden_tags": "AI Image Generators Public",
      "id": "m027",
      "url": "./events/m027",
      "highlight": false,
      "accuracy": false,
      "filters": [
        "discoveries",
        "arts"
      ],
      "img": "./assets/images/placeholders/m027.svg"
    },
    {
      "title": "Generative Media Tools",
      "intro": "<p>Widely available models draft text, images, and audio on demand.</p><p>Authorship, authenticity, and provenance become central design problems for communication systems.</p>",
      "timeline": "highlights",
      "year": 2023,
      "year_name": "",
      "year_end": 0,
      "country": [
        "US"
      ],
      "country_name": "Global",
      "hidden_tags": "compute, design, writing",
      "id": "e55",
      "url": "./events/e55",
      "highlight": false,
      "accuracy": false,
      "filters": [
        "discoveries",
        "arts",
        "aron"
      ],
      "img": "./assets/images/placeholders/e55.svg"
    }
  ]
}